cryptanalib/__init__.py
cryptanalib/classical.py
cryptanalib/frequency.py
cryptanalib/helpers.py
cryptanalib/modern.py
featherduster/__init__.py
featherduster/advice.py
featherduster/completer.py
featherduster/featherduster.py
feathermodules/__init__.py
feathermodules/auxiliary/__init__.py
feathermodules/auxiliary/base_n_solver.py
feathermodules/auxiliary/hash_format_detect.py
feathermodules/auxiliary/rand_time.py
feathermodules/block/__init__.py
feathermodules/block/aes_key_brute.py
feathermodules/block/ecb_cpa_decrypt.py
feathermodules/block/generic_padding_oracle.py
feathermodules/block/http_padding_oracle.py
feathermodules/classical/__init__.py
feathermodules/classical/alpha_shift.py
feathermodules/classical/columnar_transposition.py
feathermodules/classical/vigenere.py
feathermodules/custom/__init__.py
feathermodules/hash/__init__.py
feathermodules/hash/hash_extend.py
feathermodules/hash/pymd5.py
feathermodules/pubkey/__init__.py
feathermodules/pubkey/rsa_fermat.py
feathermodules/pubkey/rsa_wiener.py
feathermodules/stream/__init__.py
feathermodules/stream/many_time_pad.py
feathermodules/stream/multi_byte_xor.py
feathermodules/stream/single_byte_xor.py
featherduster-0.4.dist-info/LICENSE
featherduster-0.4.dist-info/METADATA
featherduster-0.4.dist-info/WHEEL
featherduster-0.4.dist-info/entry_points.txt
featherduster-0.4.dist-info/top_level.txt
featherduster-0.4.dist-info/RECORD
