Metadata-Version: 2.1
Name: featherduster
Version: 0.4
Summary: An automated, modular cryptanalysis framework (i.e. a Weapon of Math Destruction)
Home-page: http://github.com/unicornsasfuel/featherduster
Author: Daniel "unicornfurnace" Crowley
License: BSD 3-clause
Platform: UNKNOWN
Classifier: Development Status :: 4 - Beta
Classifier: Programming Language :: Python :: 2 :: Only
Classifier: Operating System :: OS Independent
Classifier: Environment :: Console :: Curses
Classifier: License :: OSI Approved :: BSD License
Classifier: Topic :: Security :: Cryptography
Requires-Dist: pycryptodome
Requires-Dist: ishell
